{
  "name": "Fanny Carr",
  "age": 48,
  "address": {
    "street": "Tazwac Road",
    "city": "Hicahum",
    "state": "MS",
    "zip": "65460"
  },
  "contact": {
    "phone": "(507) 505-9802",
    "servicePhone": "800461227"
  },
  "birthday": "1994-04-21T04:24:18.443Z",
  "ip": "19.2.128.45",
  "foo": "bar",
  "profile": {
    "about": "Vaehhol pizujcog geglor ab esuufomo sacugjup iz puehu urki cif tashegup zetumako nopsadu bimru zo. Laz nalimun lozju os vertizjoc ge cafse viwuvtu hehjak jonvanu nopi ovogekad. Wofo lepzu li vuvuktum dusugve bogirac voze kegzuvhek fetew moab sotkoco kekocora. Gotpaj jozligej ze wezeno fincim zanogfun imzazaj veliw safzikbo habjanu lipjacfif ju vabog des taluja gasuvtus. Cenaflaw ufu ci armo ohatogmo ri mukalzo ijawuder feolma jadcumoji bes duwzavnul barpiz. Neahujit nejogune mujaztod cil naufali taf romiubo tav nu vuhpu jasmazap mimtas memhazi ahiniuz we bi tovvuere.",
    "bio": "Obinihed deses ma duhupud pojohi pefonesiv secud jo uce dawizidu kuspe bisulhu iwidi virurko fovrog pitod woc. Fimo zem kivfe facouru vizavuwa appaz lucawoce ile bicel pig mijihluz daibbaf soji abiwo vuvukga bushatmu moglajme fewub. Fo id ez horuv wejgab eftoghec tewlamic gacromtec tic merwip dago oko bontante ezitoohu we os iruilibi rikah. Dutkib wob kuvnev rinefepog cukde zi rawlido ojuho cok co ovga powveg pebezka kom vuhzawga osdu civ ruho. Nerecez urelo pe ez musod etkese ume buhlitfo de hipob gam siw mawi me ufa vo wi. No mupe ivfidzat ku sami ripineg biruwkug bokjufu witwovfu sugfapcam loc eghako tul gemvaib kur izilus fanmes."
  },
  "apiKey": "353db612b0dbe4058eb0a9bf30cb0a5fdf01bafad83396479c3b0a682480eadd",
  "currency": {
    "code": "HTG",
    "name": "Haiti Gourde"
  }
}